autoline/__init__.py
autoline-1.0.3.dist-info/METADATA
autoline-1.0.3.dist-info/WHEEL
autoline-1.0.3.dist-info/top_level.txt
autoline-1.0.3.dist-info/RECORD
