Metadata-Version: 2.1
Name: autoline
Version: 1.0.3
Summary: send line message automatically
Home-page: https://pypi.org/project/autoline/
Author: KuoYuanLi
Author-email: funny4875@gmail.com
Classifier: Programming Language :: Python :: 3
Classifier: License :: OSI Approved :: MIT License
Classifier: Operating System :: OS Independent
Requires-Python: >=3.6
Requires-Dist: pyautogui
Requires-Dist: pygetwindow
Requires-Dist: pyperclip
